cliffordlayers/__init__.py
cliffordlayers/cliffordkernels.py
cliffordlayers/signature.py
cliffordlayers/version.py
cliffordlayers/models/__init__.py
cliffordlayers/models/custom_kernels.py
cliffordlayers/models/custom_layers.py
cliffordlayers/models/models_2d.py
cliffordlayers/models/models_3d.py
cliffordlayers/models/utils.py
cliffordlayers/nn/__init__.py
cliffordlayers/nn/functional/__init__.py
cliffordlayers/nn/functional/batchnorm.py
cliffordlayers/nn/functional/groupnorm.py
cliffordlayers/nn/functional/utils.py
cliffordlayers/nn/modules/__init__.py
cliffordlayers/nn/modules/batchnorm.py
cliffordlayers/nn/modules/cliffordconv.py
cliffordlayers/nn/modules/cliffordfourier.py
cliffordlayers/nn/modules/cliffordfourier_deprecated.py
cliffordlayers/nn/modules/cliffordlinear.py
cliffordlayers/nn/modules/groupnorm.py
cliffordlayers-0.1.1.dist-info/LICENSE
cliffordlayers-0.1.1.dist-info/METADATA
cliffordlayers-0.1.1.dist-info/WHEEL
cliffordlayers-0.1.1.dist-info/top_level.txt
cliffordlayers-0.1.1.dist-info/RECORD
