Metadata-Version: 2.1
Name: cliffordlayers
Version: 0.1.1
Summary: A PyTorch library for Clifford layers
Author: Jayesh K. Gupta, Johannes Brandstetter, David Ruhe, and contributors
License: MIT
Project-URL: Documentation, https://microsoft.github.io/cliffordlayers
Project-URL: Source code, https://github.com/microsoft/cliffordlayers
Project-URL: Bug tracker, https://github.com/microsoft/cliffordlayers/issues
Classifier: Programming Language :: Python :: 3
Classifier: License :: OSI Approved :: MIT License
Classifier: Operating System :: OS Independent
Classifier: Development Status :: 4 - Beta
Classifier: Topic :: Scientific/Engineering :: Artificial Intelligence
Requires-Python: >=3.6
License-File: LICENSE
Requires-Dist: torch
Requires-Dist: pytest
